zapman/__init__.py
zapman/__main__.py
zapman/_context.py
zapman/_curl.py
zapman/_exceptions.py
zapman/_io.py
zapman/_module.py
zapman/_parse.py
zapman/_print.py
zapman/_program.py
zapman/_store.py
zapman/_version.py
zapman/_zap.py
zapman/py.typed
zapman-0.0.2.dist-info/METADATA
zapman-0.0.2.dist-info/WHEEL
zapman-0.0.2.dist-info/entry_points.txt
zapman-0.0.2.dist-info/RECORD
