Metadata-Version: 2.1
Name: zapman
Version: 0.0.2
Summary: An API Client for the terminal. A Python CLI for API testing and development.
Home-page: https://github.com/lukin0110/zapman/
License: Proprietary
Requires-Python: >=3.10.0,<4.0
Classifier: License :: Other/Proprietary License
Classifier: Programming Language :: Python :: 3
Classifier: Programming Language :: Python :: 3.10
Classifier: Programming Language :: Python :: 3.11
Classifier: Programming Language :: Python :: 3.12
Classifier: Programming Language :: Python :: 3.13
Requires-Dist: httpie (>=3.2.4,<4.0.0)
Requires-Dist: orval (>=0.0.6,<0.0.7)
Project-URL: Repository, https://github.com/lukin0110/zapman/
